LICENSE
MANIFEST.in
README
README.markdown
setup.py
iboto/__init__.py
iboto/ipythonext.py
iboto.egg-info/PKG-INFO
iboto.egg-info/SOURCES.txt
iboto.egg-info/dependency_links.txt
iboto.egg-info/requires.txt
iboto.egg-info/top_level.txt
scripts/iboto