Metadata-Version: 1.0
Name: iboto
Version: 0.20.1
Summary: Amazon EC2 shell for managing multiple accounts and regions easily
Home-page: http://loads.pickle.me.uk/iboto/
Author: Barnaby Gray
Author-email: barnaby@pickle.me.uk
License: MIT
Platform: UNKNOWN
Classifier: Development Status :: 3 - Alpha
Classifier: Topic :: Utilities
Classifier: License :: OSI Approved :: MIT License
